Workbook

Sheet Ofícios
A1: CONTROLE DE OFÍCIO SIMPLES - 2025
A2: Nº | B2: Data | C2: Assunto | D2: Destino | E2: CC | F2: Responsável
A4: 1700 | B4: 45904 | C4: Solicita produção de cards sobre a disponibilização dos ônibus nos dias 8 e 11 de setembro | D4: Setor de Comunicação | F4: Raphael
A5: 1701 | B5: 45904 | C5: Solicita reserva do auditório da prefeitura para receber equipe da Escola Aprendiz de Marinheiro | D5: Gabinete | F5: Raphael
A6: 1702 | B6: 45904 | C6: Solicita pagamento da conta NEOENERGIA - Escola Madre Virgínia | D6: Secretaria de Finanças | F6: Sebastião
A7: 1703 | B7: 45904 | C7: Solicita Contratação de Monitores para ônibus que fazem as rotas na Zona Rural | D7: Gabinete | F7: Raphael
A8: 1704 | B8: 45904 | C8: Aquisição de Insumos para Almoço do dia 11 de setembro | D8: Secretaria de Governo | F8: Paula Karina
A9: 1705 | B9: 45904 | C9: Resposta ao Ofício nº 163/2025 | D9: SINDPROFM | F9: Raphael
A10: 1706 | B10: 45904 | C10: Solicita retirada de materiais de limpeza - ARTLIMP | D10: Setor de Compras | F10: Thayza
A11: 1707 | B11: 45904 | C11: Encaminha frequência da segunda quinzena de Agosto | D11: RH | F11: Lara
A12: 1708 | B12: 45904 | C12: Encaminha Nota Fiscal Pablo Luis Martins | D12: Secretaria de Finanças | F12: Raphael
A13: 1709 | B13: 45905 | C13: Encaminha DFD - Kits Escolares 2026 | D13: Secretaria de Administração | E13: Setor de Licitação | F13: Sebastião
A14: 1710 | B14: 45905 | C14: Detetização da Escola | D14: Secretaria de Governo | F14: Raphael
A15: 1711 | B15: 45905 | C15: Aluguel de Imovel Luna Filho Loja Maçonica | D15: Secretaria de Finanças | E15: Secretaria de Administração | F15: Thayza
A16: 1712 | B16: 45905 | C16: Resposta ao MP Oficio 02207.000.224/2025-0002 | D16: Ministério Publico PE | F16: Raimunda
A17: 1713 | B17: 45905 | C17: Solicita contrato de Sinthya Jeronimo da Silva e encaminha docs | D17: Gabinete | F17: Raphael
A18: 1714 | B18: 45905 | C18: Aluguel de Imovel Rancho do Himalaia | D18: Secretaria de Finanças | E18: Secretaria de Administração | F18: Thayza
A19: 1715 | B19: 45905 | C19: Aluguel de Imovel Sao Joaquim Caraúbas | D19: Secretaria de Finanças | E19: Secretaria de Administração | F19: Thayza
A20: 1716 | B20: 45905 | C20: Aluguel Imovel Madre Virginia | D20: Secretaria de Finanças | E20: Secretaria de Administração | F20: Thayza
A21: 1717 | B21: 45905 | C21: Aluguel de Imovel CEI Santa' Ana Olho Dágua | D21: Secretaria de Finanças | E21: Secretaria de Administração | F21: Thayza
A22: 1718 | B22: 45905 | C22: Aluguel de Imovel Deposito de Merenda | D22: Secretaria de Finanças | E22: Secretaria de Administração | F22: Thayza
A23: 1719 | B23: 45905 | C23: Encaminha Requerimento de Férias | D23: RH | F23: Lara
A24: 1720 | B24: 45905 | C24: Aluguel de Imovel Quadra Carauba | D24: Secretaria de Finanças | E24: Secretaria de Administração | F24: Thayza
A25: 1721 | B25: 45905 | C25: Aluguel de Imovel Casa Rosa | D25: Secretaria de Finanças | E25: Secretaria de Administração | F25: Thayza
A26: 1722 | B26: 45905 | C26: Aluguel de Imovel SEE | D26: Secretaria de Finanças | E26: Secretaria de Administração | F26: Thayza
A27: 1723 | B27: 45905 | C27: Aluguel de Imovel CEI SANTANA | D27: Secretaria de Finanças | E27: Secretaria de Administração | F27: Thayza
A28: 1724 | B28: 45905 | C28: Aluguel de Imovel CEI PETRIBU | D28: Secretaria de Finanças | E28: Secretaria de Administração | F28: Thayza
A29: 1725 | B29: 45905 | C29: Aluguel Imovel Programa Amor | D29: Secretaria de Finanças | E29: Secretaria de Administração | F29: Thayza
A30: 1726 | B30: 45905 | C30: Aluguel Imovel PIO X | D30: Secretaria de Finanças | E30: Secretaria de Administração | F30: Thayza
A31: 1727 | B31: 45905 | C31: Aluguel Nova Santa Cruz | D31: Secretaria de Finanças | E31: Secretaria de Administração | F31: Thayza
A32: 1728 | B32: 45905 | C32: Encaminhamento de planilha de licença prêmio e solicitação de portarias | D32: RH | F32: Lara
A33: 1729 | B33: 45905 | C33: Encaminha Nota Fiscal RECICOM | D33: Secretaria de Finanças | F33: Sebastião
A34: 1730 | B34: 45905 | C34: Encaminha Nota Fiscal BIZ SOLUÇÕES | D34: Secretaria de Finanças | F34: Sebastião
A35: 1731 | B35: 45905 | C35: Encaminha Nota Fiscal MP3 Distribuidora | D35: Secretaria de Finanças | F35: Sebastião
A36: 1732 | B36: 45905 | C36: Encaminha Nota Fiscal Ezata Mercantil | D36: Secretaria de Finanças | F36: Sebastião
A37: 1733 | B37: 45908 | C37: Encaminha Nota Fiscal Adriana da Silva Ferreira Delivery | D37: Secretaria de Finanças | F37: Sebastião
A38: 1734 | B38: 45909 | C38: Encaminha Nota Fiscal - Aluguel e serviços de refrigeração - Helinberg | D38: Secretaria de Finanças | F38: Sebastião
A39: 1735 | B39: 45909 | C39: Solicita contrato de Rebeca Karine de Souza Costa Correia Melo e encaminha docs | D39: Gabinete | F39: Raphael
A40: 1736 | B40: 45909 | C40: Resposta ao MP Oficio 02208.000.321/2025-0002 | D40: Ministério Publico PE | F40: Thayza
A41: 1737 | B41: 45909 | C41: Encaminha Nota Fiscal - Carmel - Compra de Corda desfile | D41: Secretaria de Finanças | F41: Sebastião
A42: 1738 | B42: 45909 | C42: Encaminha Conta Compesa - Depósito de Merenda | D42: Secretaria de Finanças | F42: Thayza
A43: 1739 | B43: 45909 | C43: Encaminha Nota Fiscal Autoforte Peças | D43: Secretaria de Finanças | F43: Sebastião
... A62: 1758 | B62: 45910 | C62: Solicitação de reparo em fossa séptica – Escola Municipal Dr. Irineu de Pontes | D62: Secretaria de Infraestrutura | F62: Thayza
A63: 1759 | B63: 45910 | C63: Comunicação de recebimentos de mercadoria | D63: Setor de Compras | E63: Secretaria de Infraestrutura | F63: Sebastião
A64: 1760 | B64: 45915 | C64: Solicita contrato de Natália Joseane da Silva e Encaminha docs | D64: Gabinete | F64: Raphael
A65: 1761 | B65: 45915 | C65: Encaminha relação de Servidores Campanha IPTU 2025 | D65: Gabinete | F65: Sebastião
A66: 1762 | B66: 45915 | C66: Solicita exoneração de Ana Cláudia Barros Barreto e pede substituto | D66: Gabinete | F66: Raphael
A67: 1763 | B67: 45915 | C67: Solicita Brinde para campeonado dos bairros (futsal) | D67: Secretaria de Cultura, Turismo e Lazer | F67: Helse Montarroyos
A68: 1764 | B68: 45915 | C68: Encaminha DFD - Materiais Gráficos - Campeonato dos Bairros de FUTSAL | D68: Setor de Licitação | E68: Secretaria de Administração | F68: Helse Montarroyos
A69: 1765 | B69: 45915 | C69: Encaminha Nota Fiscal para pagamento - VDL Gráfica | D69: Secretaria de Finanças | F69: Sebastião
A70: 1766 | B70: 45915 | C70: Solicitação Pagamento de custas Cartorarias - Escola Municipal São Joaquim | D70: Secretaria de Finanças | F70: Thayza
A71: 1767 | B71: 45915 | C71: Encaminha Nota Fiscal para pagamento - VDL Gráfica | D71: Secretaria de Finanças | F71: Sebastião
A72: 1768 | B72: 45915 | C72: Solicita a contratação de Monitora para VAN Escolar | D72: Gabinete | F72: Sebastião
A73: 1769 | B73: 45915 | C73: Encaminha Conta Neoenergia Creche Santa Terezinha | D73: Secretaria de Finanças | F73: Thayza
A74: 1770 | B74: 45915 | C74: Solicita transporte inclusivo | D74: Escola São José | F74: Raimunda
A75: 1771 | B75: 45915 | C75: Oficinas de bonecos | D75: Secretaria de Cultura, Turismo e Lazer | F75: Raimunda
A76: 1772 | B76: 45915 | C76: PROGRAMAÇÃO DESFILE DIA 21.09 E 28.09 | D76: Setor de Comunicação | F76: Thayza
A77: 1773 | B77: 45916 | C77: Solicita palco para os desfiles do Bairro Novo e Caraúba | D77: Secretaria de Cultura, Turismo e Lazer | F77: Raphael
A78: 1774 | B78: 45916 | C78: Solicita isolamento das vias e guarda para os desfiles do Bairro Novo e Caraúba | D78: Altarquia de Trânsito | F78: Raphael
A79: 1775 | B79: 45916 | C79: Solicita limpeza e iluminação para os desfiles do Bairro Novo e Caraúba | D79: Secretaria de Serviços Urbanos | F79: Raphael
A80: 1776 | B80: 45916 | C80: Solicitação de impressão das avaliações CNCA Ciclo III para os Anos Iniciais da Rede | D80: Setor de Licitação | F80: Luzinete
... A141: 1837 | B141: 45923 | C141: Solicita substituição de borrachas para atualização de informações nos carimbos | D141: Setor de Compras | F141: Lara
A142: 1838 | B142: 45923 | C142: Encaminha documento de formalização de demanda - Provas CNCA | D142: Setor de Licitação | E142: Secretaria de Administração | F142: Sebastião
A143: 1839 | B143: 45923 | C143: Encaminha conta COMPESA - CEI SANTANA | D143: Secretaria de Finanças | F143: Thayza
A144: 1840 | B144: 45923 | C144: Solicita contrato de Maria Eduarda Rodrigues Pereira de Jesus e encaminha docs | D144: Gabinete | F144: Raphael
A145: 1841 | B145: 45923 | C145: Encaminha Resposta ao MPF Resposta ao Ofício nº 5205/2025/PRPE/4° OFÍCIO | D145: Ministerio Público Federal | F145: Thayza
A146: 1842 | B146: 45924 | C146: Solicita confecção do carimbo da Escola CEI Petribú | D146: Setor de Compras | F146: Lara
A147: 1843 | B147: 45924 | C147: Encaminha NF RB COMBUSTIVEL | D147: Secretaria de Finanças | F147: Thayza
A148: 1844 | B148: 45924 | C148: Encaminha requerimento de solicitação de salário família do servidor Hygor Oliveira | D148: RH | F148: Lara
A149: 1845 | B149: 45924 | C149: Encaminha solicitação de reparos urgentes no Ernesto Ribeiro | D149: Secretaria de Infraestrutura | F149: Thayza
A150: 1846 | B150: 45924 | C150: Encaminha resposta sobre o pleito feito ao FNDE | D150: Secretaria de Planejamento e Gestão | E150: Procuradoria do Município | F150: Raphael
A151: 1847 | B151: 45924 | C151: Solicita alteração de contrato de Sonia Cristina Cordeiro de Vasconcelos | D151: Gabinete | F151: Raphael
A152: 1848 | B152: 45924 | C152: Solicita contrato de Amystesson Shunak de Assis e encaminha docs | D152: Gabinete | F152: Raphael
A153: 1849 | B153: 45924 | C153: Solicita retirada de gratificação de Susy Karla Pereira Barbosa da Hora | D153: Gabinete | F153: Raphael
A154: 1850 | B154: 45924 | C154: Solicita Prorrogação de Prazo - Contrato nº023/2025 -KUTZ | D154: Secretaria de Administração | F154: Sebastião
A155: 1851 | B155: 45924 | C155: Encaminha NF Cooperativa Mista Sao Lourenço da Mata | D155: Secretaria de Finanças | F155: Thayza
A156: 1852 | B156: 45924 | C156: Encaminha NF Cooperativa Mista Trabalhadores Rurais | D156: Secretaria de Finanças | F156: Thayza
A157: 1853 | B157: 45924 | C157: Encaminha NF George Alexandre Dias - Internet | D157: Secretaria de Finanças | F157: Thayza
A158: 1854 | B158: 45924 | C158: Encaminha NF Movéis Kutz | D158: Secretaria de Finanças | F158: Thayza
A159: 1855 | B159: 45925 | C159: Solicita desbloqueio de salário de Maria do Carmo de Freitas Santana | D159: RH | F159: Raphael
A160: 1856 | B160: 45925 | C160: Encaminha planilha de servidores que estão de licença prêmio e solicita portarias | D160: RH | F160: Lara
A161: 1857 | B161: 45925 | C161: Solicita um monitor de banheiro para a Escola Marechal Rondon | D161: Gabinete | F161: Raphael
A162: 1858 | B162: 45925 | C162: Solicita dois monitores de prédio para a Escola Pio X | D162: Gabinete | F162: Raphael
... A197: 1893 | B197: 45930 | C197: Responde ao ofício solicitando matrícula de crianças | D197: Centro de Referência Especializado de Assistência Social - CREAS | F197: Tallita
A198: 1894 | B198: 45930 | C198: Encaminha Demanda para aquisição de Absorventes | D198: Setor de Licitação | E198: Secretaria de Administração | F198: Sebastião
A199: 1895 | B199: 45930 | C199: Encaminha conta COMPESA SEE | D199: Secretaria de Finanças | F199: Thayza
A200: 1896 | B200: 45930 | C200: Encaminha Conta COMPESA CASA ROSA | D200: Secretaria de Finanças | F200: Thayza
A201: 1897 | B201: 45931 | C201: Solicita exoneração de José Atamir dos Santos | D201: Gabinete | F201: Raphael
A202: 1898 | B202: 45931 | C202: Solicita contrato de Claudionora da Silva Lima e encaminha docs | D202: Gabinete | F202: Raphael
A203: 1899 | B203: 45931 | C203: Solicita contrato de Katia Travassos da Silva e encaminha docs | D203: Gabinete | F203: Raphael
A204: 1900 | B204: 45931 | C204: Solicita exoneração de Raquel Suélen da Silva Lima Santos e substituição | D204: Gabinete | F204: Raphael
A205: 1901 | B205: 45931 | C205: Solicita exoneração de Andreza Geovania Xavier de Lima e substituição | D205: Gabinete | F205: Raphael
A206: 1902 | B206: 45931 | C206: Solicita averiguação com o jurídico sobre atestados recorrentes de cuidadores | D206: RH | F206: Raphael
A207: 1903 | B207: 45931 | C207: Solicita providências quanto ao relatorio de ocorrencia Escola Rondom | D207: Altarquia de Trânsito | F207: Thayza
A208: 1904 | B208: 45931 | C208: Informa dotação orçamentária - Quadras | D208: Secretaria de Infraestrutura | F208: Sebastião
A209: 1905 | B209: 45931 | C209: Informa dotação orçamentária - Ernestro | D209: Secretaria de Infraestrutura | F209: Sebastião
A210: 1906 | B210: 45931 | C210: Informa dotação orçamentária - Chã do Meio | D210: Secretaria de Infraestrutura | F210: Sebastião
... A220: 1916 | B220: 45932 | C220: Encaminha Nota Fiscal Cooperativa Mista - São Lourenço | D220: Secretaria de Finanças | F220: Thayza
A221: 1917 | B221: 45932 | C221: Aluguel de Imóvel Luna Filho - Rancho do Himalaia | D221: Secretaria de Finanças | E221: Secretaria de Administração | F221: Thayza
A222: 1918 | B222: 45932 | C222: Aluguel de Imóvel Luna Filho - Loja Maçonica | D222: Secretaria de Finanças | E222: Secretaria de Administração | F222: Thayza
...

Sheet < 1700
A1: CONTROLE DE OFÍCIO SIMPLES - 2025
A2: Nº | B2: Data | C2: Assunto | D2: Destino | E2: CC | F2: Responsável
A3: 1 | B3: 45660 | C3: RELATORIO DE MOBILIÁRIO | D3: Secretaria de Planejamento e Gestão
A4: 2 | B4: 45660 | C4: INFORMAÇÕES SOBRE O PETE | D4: Setor de Transportes
A5: 3 | B5: 45665 | C5: CALENDÁRIO ESCOLAR | D5: SINDPROFM
A6: 4 | B6: 45665 | C6: TERÇO DE FÉRIAS E FÉRIAS | D6: RH
A7: 5 | B7: 45665 | C7: RELAÇÃO DE CARGOS DA SEE | D7: Gabinete
A8: 6 | B8: 45665 | C8: LICENÇA PRÊMIO | D8: RH
A9: 7 | B9: 45665 | C9: ATIVAÇÃO DE CONTAS CORRENTES
A10: 8 | B10: 45665 | C10: RELAÇÃO DE NESSECIDADE DE CONTRATO | D10: Gabinete
A11: 9 | B11: 45666 | C11: TERÇO DE FÉRIAS E FÉRIAS | D11: RH
A12: 10 | B12: 45666 | C12: APOSENTARIA DE SERVIDORA | D12: RH
A13: 11 | B13: 45667 | C13: SOLICITAÇÃO DE VISTORIA SEE | D13: Secretaria de Infraestrutura
A14: 12 | B14: 45667 | C14: COMPRA DE AMTERIAL | D14: Gabinete
A15: 13 | B15: 45667 | C15: ENCAMINHAR DOCUMENTAÇÃO PESSOAL | D15: Gabinete
A16: 14 | B16: 45670 | C16: SOLICITAÇÃO DE VISTORIA | D16: Secretaria de Infraestrutura
A17: 15 | B17: 45670 | C17: SOLICITAÇÃO DE VISTORIA PRÉDIO CEI PETRIBÚ | D17: Secretaria de Infraestrutura
A18: 16 | B18: 45670 | C18: SOLICITAR ESTUDO TÉCNIVO - PERFURAÇÃO DE POÇO | D18: Secretaria de Infraestrutura
A19: 17 | B19: 45670 | C19: SOLICITAR REPAROS NAS SALAS ESC. IRINEU DE PONTES | D19: Secretaria de Infraestrutura
A20: 18 | B20: 45670 | C20: ENCAMINHAR DOCUMENTAÇÃO PESSOAL | D20: Gabinete
A21: 19 | B21: 45670 | C21: ALTERAÇÃO DE CALENDÁRIO 2025
A22: 20 | B22: 45670 | C22: ADICIONAL DE PRODUTIVIDADE | D22: RH
A23: 21 | B23: 45670 | C23: SOLICITAÇÃO MOBILIÁRIO ESCOLAR | D23: Setor de Licitação
A24: 22 | B24: 45671 | C24: SOLICITAÇÃO DE REFORMA NA CRECHE ZITE LAPA | D24: Secretaria de Infraestrutura
A25: 23 | B25: 45672 | C25: INFORMAÇÃO DA BIBLIOTECA | D25: Secretaria de Infraestrutura
A26: 24 | B26: 45672 | C26: ESTRUTURA DA SEE | D26: Gabinete
A27: 25 | B27: 45672 | C27: INFORMAR NOVO ARTICULADOR CNCA
A28: 26 | B28: 45672 | C28: INFORMAR NOVO ARTICULADOR CNCA
A29: 27 | B29: 45672 | C29: VISTORIA NA ESCOLA SÃO JOAQUIM ( VILA CARAUBA) | D29: Secretaria de Infraestrutura
A30: 28 | B30: 45672 | C30: ENCAMINHAR DOCUMENTAÇÃO PESSOAL | D30: Gabinete
A31: 29 | B31: 45673 | C31: RENOVAÇÃO DE CONTRATO SICAP | D31: Setor de Licitação
A32: 30 | B32: 45673 | C32: SOLICITAÇÕES EMERGENCIAIS | D32: Secretaria de Infraestrutura
A33: 31 | B33: 45673 | C33: ENCAMINHAR DOCUMENTAÇÃO PESSOAL | D33: Gabinete
A34: 32 | B34: 45677 | C34: INFORMAÇÃO PESSOAL SEDUC | D34: Gabinete
A35: 33 | B35: 45674 | C35: TRANSPORTE PARA VITORIA DE SANTO ANTÃO | D35: Gabinete
A36: 34 | B36: 45677 | C36: LICENÇA PRÊMIO (MARIA VERONICA) | D36: RH
A37: 35 | B37: 45677 | C37: LICENÇA PRÊMIO (MARIA VERNICA) | D37: RH
A38: 36 | B38: 45677 | C38: REMOÇÃO DE BENS EM DESUSO | D38: Secretaria de Infraestrutura
A39: 37 | B39: 45677 | C39: TERÇO DE FPERIAS E FÉRIAS | D39: RH
A40: 38 | B40: 45677 | C40: IMPRESSÃO DE CARTEIRAS TRANSPORTE | D40: Setor de Licitação
A41: 39 | B41: 45678
A42: 40 | B42: 45677 | C42: RELATORIO DE FECHAMENTO SICAP 2024 | D42: Gabinete
A43: 41 | B43: 45678 | C43: TRANSPOTE DE UNIVERSITARIOS | D43: Setor de Transportes
A44: 42 | B44: 45678 | C44: INSTALAÇÃO DE CAMERAS NA QUADRA | D44: Gabinete
A45: 43 | B45: 45678 | C45: ENCAMINHAR DOCUMENTAÇÃO PESSOAL | D45: Gabinete
A46: 44 | B46: 45678 | C46: OFÍCIO A DIRETORIA DE TRANSPORTE | D46: Secretaria de Finanças
A47: 45 | B47: 45678 | C47: CADASTRAMENTO DO SISTEMA | D47: Secretaria de Administração
A48: 46 | B48: 45678 | C48: INFORMAÇÕES SOBRE PERMUTA | D48: RH
A49: 47 | B49: 45679 | C49: DOCUMENTAÇÃO GERENCIA EDUCAÇÃO INCLUSIVA | D49: Gabinete
A50: 48 | B50: 45680 | C50: LOCAÇÃO DE POSTO DE TRABALHO | D50: Gabinete
A51: 49 | B51: 45680 | C51: REENCAMINHAMENTO CALENDÁRIO | D51: Gabinete
A52: 50 | B52: 45680 | C52: SEC. ASSISTENCIA SOCIAL / CONSELHO | D52: Secretaria de Desenvolvimento Social, Criança e Juventude
A53: 51 | B53: 45680 | C53: SEC. SAÚDE / KIT CILINDRO | D53: Secretaria de Saúde
... A64: 62 | B64: 45684 | C64: ESCOLAS CONFESSIONAIS | D64: Gabinete
A65: 63 | B65: ------ | C65: ------------------------------------------
A66: 64 | B66: ------ | C66: ------------------------------------------
A67: 65 | B67: ------ | C67: ------------------------------------------
A68: 66 | B68: 45686 | C68: SOLICITAÇÃO DE SENHA SIOPE | D68: Setor de Comunicação
A69: 67 | B69: 45687 | C69: AQUISIÇÃO DE CRACHAS PARA TRANSPOTES | D69: Secretaria de Administração
A70: 68 | B70: 45687 | C70: SOLITAÇÃO LOCAÇÃO E AQUISIÇÃO DE VEICULOS .... | D70: Secretaria de Administração
A71: 69 | B71: 45687 | C71: SOLITAÇÃO LOCAÇÃO E AQUISIÇÃO DE VEICULOS | D71: Secretaria de Administração
A72: 70 | B72: 45687 | C72: EXCLUSÃO DE SERVIDOR | D72: RH
A73: 71 | B73: 45687 | C73: DESLIGAMENTO DE SERVIDOR | D73: RH
A74: 72 | B74: 45687 | C74: DOCUMENTAÇÃO DE SERVIDOR DA ESCOLA BELA VIST A | D74: RH
A75: 73 | B75: 45687 | C75: EMPRESA PARA MANUTENÇÃO DE PISCINA | D75: Secretaria de Administração
A76: 74 | B76: 45687 | C76: RESPOSTA AO OFÍCIO MPPE | D76: Ministerio Público Federal
A77: 75 | B77: 45687 | C77: RESPOSTA AO OFÍCIO MPPE | D77: Ministerio Público Federal
A78: 76 | B78: 45687 | C78: CEDENCIA DE SERVIDOR EFETIVO | D78: Gabinete
A79: 77 | B79: 45687 | C79: RENOVAÇÃO DE PERMUTA | D79: Gabinete
... A103: 101 | B103: 45694 | C103: ALUGUEL DE GALPÃO | D103: Secretaria de Governo
A104: 102 | B104: 45695
A105: 103 | B105: 45695 | C105: MUDANÇA DE FAIXA SALARIAL | D105: RH
A106: 104 | B106: 45695 | C106: SOLICITAÇÃO DE MATERIAL ESPORTIVO | D106: Secretaria de Finanças
A107: 105 | B107: 45696 | C107: ------------------------- | D107: Secretaria de Finanças
A108: 106 | B108: 45696 | C108: ------------------------- | D108: Ministério Publico PE
A109: 107 | B109: 45696 | C109: ------------------------- | D109: Secretaria de Administração
A110: 108 | B110: 45699 | C110: LICENÇA PRÊMIO | D110: RH
A111: 109 | B111: 45699 | C111: SOLICITAR SALAS MADRE VIRGINIA | D111: Gabinete
A112: 110 | B112: 45699 | C112: PARECER JÚRIDICO | D112: Procuradoria do Município
A113: 111 | B113: 45700 | C113: ADESÃO DE ATA | D113: Secretaria de Finanças
A114: 112 | B114: 45700 | C114: RELAÇÃO DE GESTORES ESCOLARES | D114: Gabinete
A115: 113 | B115: 45700 | D115: Ministerio Público Federal
A116: 114 | B116: 45700 | C116: RELAÇÃO DE GESTORES ESCOLARES | D116: Gabinete
A117: 115 | B117: 45700 | C117: RELAÇÃO DE MOTORISTAS | D117: Gabinete
A118: 116 | B118: 45701 | C118: TERMO DE CONVENIOS | D118: Gabinete
A119: 117 | B119: 45701 | C119: TERÇO DE FÉRIAS | D119: RH
A120: 118 | B120: 45701 | C120: DOCUMENTAÇÃO DE GESTOR JORGE MIGUEL | D120: Gabinete
A121: 119 | B121: 45701 | C121: DECLARAÇÃO DE ACUMULO DE CARGO | D121: RH
A122: 120 | B122: 45701 | C122: DESVINCULAÇÃO DE SINDICATO | D122: RH
A123: 121 | B123: 45701 | C123: TERÇO DE FÉRIAS E FÉRIAS | D123: RH
A124: 122 | B124: 45701 | C124: LICENÇA PRÊMIO | D124: RH
A125: 123 | B125: 45701 | C125: CRONOGRAMA PSE | D125: Secretaria de Saúde
A126: 124 | B126: 45701 | C126: DOCUMENTAÇÃO DE SERVIDORES | D126: Gabinete
A127: 125 | B127: 45701 | C127: DOCUMENTAÇÃO DE SERVIDORES SEC. ESPORTE | D127: Gabinete
... A142: 140 | B142: 45706 | C142: AQUISIÇÃO DE CAIXAS DE OFÍCIO | D142: Secretaria de Finanças
A143: 141 | B143: 45706
A144: 142 | B144: 45706 | C144: SOLICITAÇÃO DE EQUIPE DE PALESTRAS LEI LUCAS | D144: Secretaria de Saúde
A145: 143 | B145: 45706 | C145: SOLICITAÇÃO DE MATERIAIS DIDATICOS | D145: Secretaria de Finanças
A146: 144 | B146: 45706 | C146: APOIO DA GUARDA MUNICIPAL | D146: Gabinete
A147: 145 | B147: 45708 | C147: RELAÇÃO DE MOTORISTA TRANSPORTE ESCOLAR | D147: Gabinete
...

Sheet Ofícios Circulares
A1: CONTROLE DE OFÍCIO CIRCULARES - 2025
A2: Nº | B2: Data | C2: Assunto | D2: Destinos | E2: Responsável
A3: 25 | B3: 09/04/2025 | C3: Convite para evento com Escola de Aprendiz de Marinheiro no Auditório da Prefeitura | D3: Escolas de Carpina | E3: Raphael
A4: 26 | B4: 06/10/2025 | C4: Expedientes dia 08 e 12 | D4: Escolas Municipais | E4: Raphael
A5: 27 | B5: 06/10/2025 | C5: Comunica sobre a Transferência dos feriados dos dias 15 e 28 | D5: Escolas Municipais | E5: Raphael
A6: 28 | B6: 07/10/2025 | C6: Solicita o uso de detectores de metais nas escolas | D6: Escolas Municipais | E6: Ana Christine
A7: 29 | B7: 08/10/2025 | C7: Informa a data de aplicação das provas do SAEB | D7: Escolas Municipais | E7: Raimunda
A8: 30
A9: 31
A10: 32
A11: 33
A12: 34
A13: 35
A14: 36
A15: 37
A16: 38
A17: 39
A18: 40
A19: 41
... A478: 500

Sheet Dados
A2: Destinos | C2: Responsáveis
A3: Gabinete | B3: Diogo Prado | C3: Ana Christine
A4: RH | B4: Kassia Vera Cruz Zamorano Grassi | C4: Ana Paula
A5: Secretaria da Mulher | B5: Izaura Pessoa | C5: Almir
A6: Secretaria de Administração | B6: Izaura Pessoa | C6: Edson
A7: Secretaria de Cultura, Turismo e Lazer | B7: Marta Guerra | C7: Fabrício
A8: Secretaria de Desenvolvimento Econômico, Indústria e Comércio | B8: Rafaela Britto | C8: Flávia
A9: Secretaria de Desenvolvimento Social, Criança e Juventude | B9: Marcelo Pascoal | C9: Lara
A10: Secretaria de Educação e Esportes | B10: Rosejara Ramos | C10: Luzinete
A11: Secretaria de Finanças | B11: Lucas Israel | C11: Luzivânia
A12: Secretaria de Infraestrutura | B12: Tiago Grassi | C12: Paula Karina
A13: Secretaria de Meio Ambiente e da Causa Animal | B13: Giovanni José | C13: Raimunda
A14: Secretaria de Planejamento e Gestão | B14: Marcelo Gomes | C14: Raphael
... A17: Setor de Comunicação | B17: Stefhane Hellem | C17: Tallita
A18: Escolas de Carpina | C18: Thayza
A19: Escolas Estaduais | C19: Tiago
A20: Escolas Municipais | C20: Helse Montarroyos
A21: Secretaria de Governo | B21: Roberval Araújo
A22: Setor de Compras | B22: Rafael Araújo
A23: Wiguivaldo Patriota Santos
A24: Ministério Publico PE
A25: Gerencia de TI
A26: Controladoria Geral Municipio de Carpina
A27: Autarquia de Trânsito | B27: Jorge Lapa
A28: Secretaria de Serviços Urbanos | B28: Rodrigo Pires
A29: Escola São José
A30: Setor de Transportes | B30: Silvio Mendes
A31: Movimento Reflorestando Carpina
A32: Policia Militar de Carpina
A33: Secretario de Serviços Urbanos
A34: Secretaria Executiva de Administração
A35: Procuradoria do Município
A36: Ministerio Público Federal
A37: Escola Pio X
A38: Escola Eliane Carneiro
A39: Escola Santa Ana
A40: Escola Mínima de Florestinha
A41: Centro de Referência Especializado de Assistência Social - CREAS
A42: Presidente CAE/CME
... A59: Diretoria de Transportes

Sheet Dashboard
B1: Cadastrados <1700 | C1: =COUNTA('< 1700'!B3:B1701) -> 592 | D1: Cadastrados total | E1: =COUNTA('Ofícios'!$B$4:$B$1304) -> 621
B2: Faltando: | C2: =1700-C1 -> 1108 | D2: Não vazias | E2: =E1+C1 -> 1213
B4: Total de ofícios: | H4: Total de ofícios registrados: | M4: Total de ofícios a serem registrados:
B5: =C2+E2 -> 2321 | H5: =E2 -> 1213 | M5: =C2 -> 1108
B11: Total de ofícios por responsáveis: | H11: Total de ofícios por meses:
B12: =Dados!C3 -> Ana Christine | F12: =COUNTIF('Ofícios'!F:F, B12) -> 2 | H12: Janeiro | I12: =SUMPRODUCT((MONTH('Ofícios'!B4:B1001)=1)*(ISNUMBER('Ofícios'!B4:B1001))) -> #VALUE!
B13: =Dados!C4 -> Ana Paula | F13: =COUNTIF('Ofícios'!F:F, B13) -> 0 | H13: Fevereiro | I13: =SUMPRODUCT((MONTH('Ofícios'!B4:B1001)=2)*(ISNUMBER('Ofícios'!B4:B1001))) -> #VALUE!
B14: =Dados!C5 -> Almir | F14: =COUNTIF('Ofícios'!F:F, B14) -> 66 | H14: Março | I14: =SUMPRODUCT((MONTH('Ofícios'!B4:B1001)=3)*(ISNUMBER('Ofícios'!B4:B1001))) -> #VALUE!
B15: =Dados!C6 -> Edson | F15: =COUNTIF('Ofícios'!F:F, B15) -> 0 | H15: Abril | I15: =SUMPRODUCT((MONTH('Ofícios'!B4:B1001)=4)*(ISNUMBER('Ofícios'!B4:B1001))) -> #VALUE!
B16: =Dados!C7 -> Fabrício | F16: =COUNTIF('Ofícios'!F:F, B16) -> 0 | H16: Maio | I16: =SUMPRODUCT((MONTH('Ofícios'!B4:B1001)=5)*(ISNUMBER('Ofícios'!B4:B1001))) -> #VALUE!
B17: =Dados!C8 -> Flávia | F17: =COUNTIF('Ofícios'!F:F, B17) -> 0 | H17: Junho | I17: =SUMPRODUCT((MONTH('Ofícios'!B4:B1001)=6)*(ISNUMBER('Ofícios'!B4:B1001))) -> #VALUE!
B18: =Dados!C9 -> Lara | F18: =COUNTIF('Ofícios'!F:F, B18) -> 40 | H18: Julho | I18: =SUMPRODUCT((MONTH('Ofícios'!B4:B1001)=7)*(ISNUMBER('Ofícios'!B4:B1001))) -> #VALUE!
B19: =Dados!C10 -> Luzinete | F19: =COUNTIF('Ofícios'!F:F, B19) -> 6 | H19: Agosto | I19: =SUMPRODUCT((MONTH('Ofícios'!B4:B1001)=8)*(ISNUMBER('Ofícios'!B4:B1001))) -> #VALUE!
B20: =Dados!C11 -> Luzivânia | F20: =COUNTIF('Ofícios'!F:F, B20) -> 0 | H20: Setembro | I20: =SUMPRODUCT((MONTH('Ofícios'!B4:B1001)=9)*(ISNUMBER('Ofícios'!B4:B1001))) -> #VALUE!
B21: =Dados!C12 -> Paula Karina | F21: =COUNTIF('Ofícios'!F:F, B21) -> 13 | H21: Outubro | I21: =SUMPRODUCT((MONTH('Ofícios'!B4:B1001)=10)*(ISNUMBER('Ofícios'!B4:B1001))) -> #VALUE!
B22: =Dados!C13 -> Raimunda | F22: =COUNTIF('Ofícios'!F:F, B22) -> 5 | H22: Novembro | I22: =SUMPRODUCT((MONTH('Ofícios'!B4:B1001)=11)*(ISNUMBER('Ofícios'!B4:B1001))) -> #VALUE!
B23: =Dados!C14 -> Raphael | F23: =COUNTIF('Ofícios'!F:F, B23) -> 183 | H23: Dezembro | I23: =SUMPRODUCT((MONTH('Ofícios'!B4:B1001)=12)*(ISNUMBER('Ofícios'!B4:B1001))) -> #VALUE!
B24: =Dados!C15 -> Rúbia | F24: =COUNTIF('Ofícios'!F:F, B24) -> 2
B25: =Dados!C16 -> Sebastião | F25: =COUNTIF('Ofícios'!F:F, B25) -> 103
B26: =Dados!C17 -> Tallita | F26: =COUNTIF('Ofícios'!F:F, B26) -> 10
B27: =Dados!C18 -> Thayza | F27: =COUNTIF('Ofícios'!F:F, B27) -> 171
B28: =Dados!C19 -> Tiago | F28: =COUNTIF('Ofícios'!F:F, B28) -> 0
B29: =Dados!C20 -> Helse Montarroyos | F29: =COUNTIF('Ofícios'!F:F, B29) -> 19
